suanpan/__init__.py
suanpan/base.py
suanpan/g.py
suanpan/imports.py
suanpan/log.py
suanpan/run.py
suanpan/api/__init__.py
suanpan/api/base.py
suanpan/app/__init__.py
suanpan/app/arguments.py
suanpan/app/base.py
suanpan/arguments/__init__.py
suanpan/arguments/base.py
suanpan/configs/defaultEnvs.yaml
suanpan/http_server/__init__.py
suanpan/http_server/server.py
suanpan/socket_io_server/__init__.py
suanpan/socket_io_server/server.py
suanpan/storage/__init__.py
suanpan/storage/base.py
suanpan/stream/__init__.py
suanpan/stream/base.py
suanpan/utils/__init__.py
suanpan/utils/config.py
suanpan/utils/port.py
suanpan/utils/tools.py
python_suanpan_slim-1.0.28.dist-info/METADATA
python_suanpan_slim-1.0.28.dist-info/WHEEL
python_suanpan_slim-1.0.28.dist-info/top_level.txt
python_suanpan_slim-1.0.28.dist-info/RECORD
